{
  "updated": "2026-06-05T16:25:33.192015+00:00",
  "quotes": {
    "MELI": {
      "price": 1616.01,
      "change": -18.77,
      "changePercent": -1.15,
      "high": 1650.2,
      "low": 1614.0,
      "prevClose": 1634.78
    },
    "IBN": {
      "price": 26.0,
      "change": -0.09,
      "changePercent": -0.34,
      "high": 26.28,
      "low": 25.86,
      "prevClose": 26.09
    },
    "NU": {
      "price": 12.06,
      "change": -0.06,
      "changePercent": -0.49,
      "high": 12.35,
      "low": 12.02,
      "prevClose": 12.12
    },
    "SSNLF": {
      "price": 140.0,
      "change": 74.79,
      "changePercent": 114.69,
      "high": 140.0,
      "low": 140.0,
      "prevClose": 65.21
    },
    "GGAL": {
      "price": 47.51,
      "change": -1.11,
      "changePercent": -2.28,
      "high": 48.71,
      "low": 47.46,
      "prevClose": 48.62
    },
    "RJHI": {
      "price": 96.5,
      "change": 0.5,
      "changePercent": 0.52,
      "high": 97.0,
      "low": 95.8,
      "prevClose": 96.0
    },
    "ASTS": {
      "price": 94.62,
      "change": -12.67,
      "changePercent": -11.81,
      "high": 104.49,
      "low": 94.16,
      "prevClose": 107.29
    },
    "RKLB": {
      "price": 111.88,
      "change": -8.07,
      "changePercent": -6.73,
      "high": 117.98,
      "low": 111.18,
      "prevClose": 119.95
    },
    "OKLO": {
      "price": 59.33,
      "change": -6.06,
      "changePercent": -9.27,
      "high": 65.47,
      "low": 58.96,
      "prevClose": 65.39
    },
    "LUNR": {
      "price": 29.77,
      "change": -3.86,
      "changePercent": -11.48,
      "high": 33.01,
      "low": 29.5,
      "prevClose": 33.63
    },
    "KSPI": {
      "price": 81.95,
      "change": -1.46,
      "changePercent": -1.75,
      "high": 84.32,
      "low": 80.44,
      "prevClose": 83.41
    },
    "GRAB": {
      "price": 3.38,
      "change": -0.08,
      "changePercent": -2.31,
      "high": 3.44,
      "low": 3.35,
      "prevClose": 3.46
    },
    "SE": {
      "price": 86.22,
      "change": -5.87,
      "changePercent": -6.37,
      "high": 91.62,
      "low": 86.05,
      "prevClose": 92.09
    },
    "STNE": {
      "price": 10.59,
      "change": -0.17,
      "changePercent": -1.58,
      "high": 11.01,
      "low": 10.53,
      "prevClose": 10.76
    },
    "GLOB": {
      "price": 37.96,
      "change": -1.62,
      "changePercent": -4.09,
      "high": 41.04,
      "low": 37.69,
      "prevClose": 39.58
    },
    "IONQ": {
      "price": 58.33,
      "change": -7.33,
      "changePercent": -11.16,
      "high": 63.79,
      "low": 58.0,
      "prevClose": 65.66
    },
    "JOBY": {
      "price": 9.9,
      "change": -1.24,
      "changePercent": -11.13,
      "high": 10.97,
      "low": 9.82,
      "prevClose": 11.14
    },
    "RDW": {
      "price": 18.61,
      "change": -2.82,
      "changePercent": -13.16,
      "high": 21.19,
      "low": 18.5,
      "prevClose": 21.43
    },
    "DAVE": {
      "price": 261.49,
      "change": -0.2,
      "changePercent": -0.08,
      "high": 266.75,
      "low": 256.7,
      "prevClose": 261.69
    }
  }
}