{
  "updated": "2026-07-13T16:21:27.185173+00:00",
  "quotes": {
    "MELI": {
      "price": 1872.93,
      "change": 20.71,
      "changePercent": 1.12,
      "high": 1897.26,
      "low": 1856.64,
      "prevClose": 1852.22
    },
    "IBN": {
      "price": 29.22,
      "change": 0.22,
      "changePercent": 0.76,
      "high": 29.45,
      "low": 29.19,
      "prevClose": 29.0
    },
    "NU": {
      "price": 13.77,
      "change": 0.01,
      "changePercent": 0.07,
      "high": 13.87,
      "low": 13.61,
      "prevClose": 13.76
    },
    "SSNLF": {
      "price": 140.0,
      "change": 74.79,
      "changePercent": 114.69,
      "high": 140.0,
      "low": 140.0,
      "prevClose": 65.21
    },
    "GGAL": {
      "price": 52.53,
      "change": -1.2,
      "changePercent": -2.23,
      "high": 54.03,
      "low": 51.88,
      "prevClose": 53.73
    },
    "RJHI": {
      "price": 96.5,
      "change": 0.5,
      "changePercent": 0.52,
      "high": 97.0,
      "low": 95.8,
      "prevClose": 96.0
    },
    "ASTS": {
      "price": 69.2,
      "change": -4.12,
      "changePercent": -5.62,
      "high": 72.54,
      "low": 68.9,
      "prevClose": 73.32
    },
    "RKLB": {
      "price": 77.41,
      "change": -3.63,
      "changePercent": -4.48,
      "high": 79.97,
      "low": 77.05,
      "prevClose": 81.04
    },
    "OKLO": {
      "price": 45.91,
      "change": -2.94,
      "changePercent": -6.02,
      "high": 48.12,
      "low": 45.87,
      "prevClose": 48.85
    },
    "LUNR": {
      "price": 15.82,
      "change": -0.32,
      "changePercent": -1.98,
      "high": 16.03,
      "low": 15.43,
      "prevClose": 16.14
    },
    "KSPI": {
      "price": 89.43,
      "change": -0.24,
      "changePercent": -0.27,
      "high": 91.74,
      "low": 89.21,
      "prevClose": 89.67
    },
    "GRAB": {
      "price": 4.0,
      "change": 0.07,
      "changePercent": 1.78,
      "high": 4.06,
      "low": 3.93,
      "prevClose": 3.93
    },
    "SE": {
      "price": 112.62,
      "change": 1.48,
      "changePercent": 1.33,
      "high": 115.54,
      "low": 111.0,
      "prevClose": 111.14
    },
    "STNE": {
      "price": 11.3,
      "change": 0.09,
      "changePercent": 0.8,
      "high": 11.34,
      "low": 11.09,
      "prevClose": 11.21
    },
    "GLOB": {
      "price": 32.07,
      "change": 2.11,
      "changePercent": 7.04,
      "high": 32.27,
      "low": 30.54,
      "prevClose": 29.96
    },
    "IONQ": {
      "price": 39.28,
      "change": -3.58,
      "changePercent": -8.35,
      "high": 42.18,
      "low": 39.2,
      "prevClose": 42.86
    },
    "JOBY": {
      "price": 7.5,
      "change": -0.22,
      "changePercent": -2.85,
      "high": 7.63,
      "low": 7.44,
      "prevClose": 7.72
    },
    "RDW": {
      "price": 9.72,
      "change": -0.46,
      "changePercent": -4.52,
      "high": 10.14,
      "low": 9.62,
      "prevClose": 10.18
    },
    "DAVE": {
      "price": 397.63,
      "change": -3.12,
      "changePercent": -0.78,
      "high": 408.96,
      "low": 383.48,
      "prevClose": 400.75
    }
  }
}